[
   {
      "results": [
         {
            "library_name": "jsonifier",
            "result_type": "Read",
            "result_speed": 66.58439070147517,
            "color": "teal"
         },
         {
            "library_name": "jsonifier",
            "result_type": "Write",
            "result_speed": 13.654180091932242,
            "color": "steelblue"
         },
         {
            "library_name": "glaze",
            "result_type": "Read",
            "result_speed": 49.609819013023596,
            "color": "dodgerblue"
         },
         {
            "library_name": "glaze",
            "result_type": "Write",
            "result_speed": 37.28573724509408,
            "color": "skyblue"
         },
         {
            "library_name": "simdjson",
            "result_type": "Read",
            "result_speed": 25.651387789919777,
            "color": "cadetblue"
         }
      ],
      "test_name": "Double Test"
   },
   {
      "results": [
         {
            "library_name": "glaze",
            "result_type": "Read",
            "result_speed": 173.2450074144299,
            "color": "dodgerblue"
         },
         {
            "library_name": "glaze",
            "result_type": "Write",
            "result_speed": 212.64255627164417,
            "color": "skyblue"
         },
         {
            "library_name": "simdjson",
            "result_type": "Read",
            "result_speed": 122.04683662401212,
            "color": "cadetblue"
         },
         {
            "library_name": "jsonifier",
            "result_type": "Read",
            "result_speed": 101.94438478204684,
            "color": "teal"
         },
         {
            "library_name": "jsonifier",
            "result_type": "Write",
            "result_speed": 99.47982841877712,
            "color": "steelblue"
         }
      ],
      "test_name": "String Test"
   },
   {
      "results": [
         {
            "library_name": "jsonifier",
            "result_type": "Read",
            "result_speed": 154.73991266603522,
            "color": "teal"
         },
         {
            "library_name": "jsonifier",
            "result_type": "Write",
            "result_speed": 106.99227219518487,
            "color": "steelblue"
         },
         {
            "library_name": "glaze",
            "result_type": "Read",
            "result_speed": 132.00563227750803,
            "color": "dodgerblue"
         },
         {
            "library_name": "glaze",
            "result_type": "Write",
            "result_speed": 143.36927315578936,
            "color": "skyblue"
         },
         {
            "library_name": "simdjson",
            "result_type": "Read",
            "result_speed": 60.137168973158694,
            "color": "cadetblue"
         }
      ],
      "test_name": "Uint Test"
   },
   {
      "results": [
         {
            "library_name": "jsonifier",
            "result_type": "Read",
            "result_speed": 158.95780893492883,
            "color": "teal"
         },
         {
            "library_name": "jsonifier",
            "result_type": "Write",
            "result_speed": 107.49311442587381,
            "color": "steelblue"
         },
         {
            "library_name": "glaze",
            "result_type": "Read",
            "result_speed": 135.29642957179468,
            "color": "dodgerblue"
         },
         {
            "library_name": "glaze",
            "result_type": "Write",
            "result_speed": 137.62687780603954,
            "color": "skyblue"
         },
         {
            "library_name": "simdjson",
            "result_type": "Read",
            "result_speed": 66.62408128966135,
            "color": "cadetblue"
         }
      ],
      "test_name": "Int Test"
   },
   {
      "results": [
         {
            "library_name": "jsonifier",
            "result_type": "Read",
            "result_speed": 68.8314091894802,
            "color": "teal"
         },
         {
            "library_name": "jsonifier",
            "result_type": "Write",
            "result_speed": 87.5936491570018,
            "color": "steelblue"
         },
         {
            "library_name": "glaze",
            "result_type": "Read",
            "result_speed": 35.92518547899907,
            "color": "dodgerblue"
         },
         {
            "library_name": "glaze",
            "result_type": "Write",
            "result_speed": 33.03390282099777,
            "color": "skyblue"
         },
         {
            "library_name": "simdjson",
            "result_type": "Read",
            "result_speed": 17.860650949291475,
            "color": "cadetblue"
         }
      ],
      "test_name": "Bool Test"
   },
   {
      "results": [
         {
            "library_name": "jsonifier",
            "result_type": "Read",
            "result_speed": 723.0687695008448,
            "color": "teal"
         },
         {
            "library_name": "jsonifier",
            "result_type": "Write",
            "result_speed": 796.1358189451814,
            "color": "steelblue"
         },
         {
            "library_name": "glaze",
            "result_type": "Read",
            "result_speed": 639.1548240013685,
            "color": "dodgerblue"
         },
         {
            "library_name": "glaze",
            "result_type": "Write",
            "result_speed": 567.4573892354466,
            "color": "skyblue"
         },
         {
            "library_name": "simdjson",
            "result_type": "Read",
            "result_speed": 531.1451877583597,
            "color": "cadetblue"
         }
      ],
      "test_name": "Json Test (Prettified)"
   },
   {
      "results": [
         {
            "library_name": "glaze",
            "result_type": "Read",
            "result_speed": 546.0102639200674,
            "color": "dodgerblue"
         },
         {
            "library_name": "glaze",
            "result_type": "Write",
            "result_speed": 461.2387300130364,
            "color": "skyblue"
         },
         {
            "library_name": "jsonifier",
            "result_type": "Read",
            "result_speed": 545.5949937294613,
            "color": "teal"
         },
         {
            "library_name": "jsonifier",
            "result_type": "Write",
            "result_speed": 690.2218946093228,
            "color": "steelblue"
         },
         {
            "library_name": "simdjson",
            "result_type": "Read",
            "result_speed": 397.30931238769165,
            "color": "cadetblue"
         }
      ],
      "test_name": "Json Test (Minified)"
   },
   {
      "results": [
         {
            "library_name": "simdjson",
            "result_type": "Read",
            "result_speed": 503.3090437064463,
            "color": "cadetblue"
         },
         {
            "library_name": "jsonifier",
            "result_type": "Read",
            "result_speed": 183.08323157729785,
            "color": "teal"
         },
         {
            "library_name": "jsonifier",
            "result_type": "Write",
            "result_speed": 747.1971962041101,
            "color": "steelblue"
         }
      ],
      "test_name": "Partial Test (Prettified)"
   },
   {
      "results": [
         {
            "library_name": "simdjson",
            "result_type": "Read",
            "result_speed": 399.69084290274606,
            "color": "cadetblue"
         },
         {
            "library_name": "jsonifier",
            "result_type": "Read",
            "result_speed": 139.3531084177186,
            "color": "teal"
         },
         {
            "library_name": "jsonifier",
            "result_type": "Write",
            "result_speed": 717.8835022501099,
            "color": "steelblue"
         }
      ],
      "test_name": "Partial Test (Minified)"
   },
   {
      "results": [
         {
            "library_name": "jsonifier",
            "result_type": "Read",
            "result_speed": 719.4339286648299,
            "color": "teal"
         },
         {
            "library_name": "jsonifier",
            "result_type": "Write",
            "result_speed": 650.2408414204748,
            "color": "steelblue"
         },
         {
            "library_name": "glaze",
            "result_type": "Read",
            "result_speed": 667.2606596222939,
            "color": "dodgerblue"
         },
         {
            "library_name": "glaze",
            "result_type": "Write",
            "result_speed": 430.9726262882418,
            "color": "skyblue"
         },
         {
            "library_name": "simdjson",
            "result_type": "Read",
            "result_speed": 536.0432805791444,
            "color": "cadetblue"
         }
      ],
      "test_name": "Abc (Out of Order) Test (Prettified)"
   },
   {
      "results": [
         {
            "library_name": "jsonifier",
            "result_type": "Read",
            "result_speed": 524.818228530118,
            "color": "teal"
         },
         {
            "library_name": "jsonifier",
            "result_type": "Write",
            "result_speed": 706.4331861923234,
            "color": "steelblue"
         },
         {
            "library_name": "glaze",
            "result_type": "Read",
            "result_speed": 519.3973979063902,
            "color": "dodgerblue"
         },
         {
            "library_name": "glaze",
            "result_type": "Write",
            "result_speed": 436.42796910679306,
            "color": "skyblue"
         },
         {
            "library_name": "simdjson",
            "result_type": "Read",
            "result_speed": 382.5248805605726,
            "color": "cadetblue"
         }
      ],
      "test_name": "Abc (Out of Order) Test (Minified)"
   },
   {
      "results": [
         {
            "library_name": "jsonifier",
            "result_type": "Read",
            "result_speed": 746.8807493924534,
            "color": "teal"
         },
         {
            "library_name": "jsonifier",
            "result_type": "Write",
            "result_speed": 970.4160186921642,
            "color": "steelblue"
         },
         {
            "library_name": "glaze",
            "result_type": "Read",
            "result_speed": 692.0965376504389,
            "color": "dodgerblue"
         },
         {
            "library_name": "glaze",
            "result_type": "Write",
            "result_speed": 622.6629857164359,
            "color": "skyblue"
         },
         {
            "library_name": "simdjson",
            "result_type": "Read",
            "result_speed": 414.47919374595057,
            "color": "cadetblue"
         }
      ],
      "test_name": "Discord Test (Prettified)"
   },
   {
      "results": [
         {
            "library_name": "glaze",
            "result_type": "Read",
            "result_speed": 578.0517521838698,
            "color": "dodgerblue"
         },
         {
            "library_name": "glaze",
            "result_type": "Write",
            "result_speed": 640.803290495182,
            "color": "skyblue"
         },
         {
            "library_name": "jsonifier",
            "result_type": "Read",
            "result_speed": 538.3806665925833,
            "color": "teal"
         },
         {
            "library_name": "jsonifier",
            "result_type": "Write",
            "result_speed": 810.2855265948889,
            "color": "steelblue"
         },
         {
            "library_name": "simdjson",
            "result_type": "Read",
            "result_speed": 255.0609086426858,
            "color": "cadetblue"
         }
      ],
      "test_name": "Discord Test (Minified)"
   },
   {
      "results": [
         {
            "library_name": "jsonifier",
            "result_type": "Read",
            "result_speed": 580.1598994948608,
            "color": "teal"
         },
         {
            "library_name": "jsonifier",
            "result_type": "Write",
            "result_speed": 1060.9259747917285,
            "color": "steelblue"
         },
         {
            "library_name": "glaze",
            "result_type": "Read",
            "result_speed": 523.6594302540732,
            "color": "dodgerblue"
         },
         {
            "library_name": "glaze",
            "result_type": "Write",
            "result_speed": 619.7207739975377,
            "color": "skyblue"
         },
         {
            "library_name": "simdjson",
            "result_type": "Read",
            "result_speed": 457.18119116901306,
            "color": "cadetblue"
         }
      ],
      "test_name": "Canada Test (Prettified)"
   },
   {
      "results": [
         {
            "library_name": "jsonifier",
            "result_type": "Read",
            "result_speed": 216.31433170799005,
            "color": "teal"
         },
         {
            "library_name": "jsonifier",
            "result_type": "Write",
            "result_speed": 469.08767384503597,
            "color": "steelblue"
         },
         {
            "library_name": "glaze",
            "result_type": "Read",
            "result_speed": 204.85348409637723,
            "color": "dodgerblue"
         },
         {
            "library_name": "glaze",
            "result_type": "Write",
            "result_speed": 363.19262947111264,
            "color": "skyblue"
         },
         {
            "library_name": "simdjson",
            "result_type": "Read",
            "result_speed": 149.29218849393135,
            "color": "cadetblue"
         }
      ],
      "test_name": "Canada Test (Minified)"
   },
   {
      "results": [
         {
            "library_name": "jsonifier",
            "result_type": "Read",
            "result_speed": 984.0666669121686,
            "color": "teal"
         },
         {
            "library_name": "jsonifier",
            "result_type": "Write",
            "result_speed": 1440.042132064451,
            "color": "steelblue"
         },
         {
            "library_name": "glaze",
            "result_type": "Read",
            "result_speed": 913.3534269168933,
            "color": "dodgerblue"
         },
         {
            "library_name": "glaze",
            "result_type": "Write",
            "result_speed": 640.7820874585607,
            "color": "skyblue"
         },
         {
            "library_name": "simdjson",
            "result_type": "Read",
            "result_speed": 588.1589553225969,
            "color": "cadetblue"
         }
      ],
      "test_name": "CitmCatalog Test (Prettified)"
   },
   {
      "results": [
         {
            "library_name": "glaze",
            "result_type": "Read",
            "result_speed": 512.9976498638039,
            "color": "dodgerblue"
         },
         {
            "library_name": "glaze",
            "result_type": "Write",
            "result_speed": 406.95231891217645,
            "color": "skyblue"
         },
         {
            "library_name": "jsonifier",
            "result_type": "Read",
            "result_speed": 494.7297697085102,
            "color": "teal"
         },
         {
            "library_name": "jsonifier",
            "result_type": "Write",
            "result_speed": 944.1855109821365,
            "color": "steelblue"
         },
         {
            "library_name": "simdjson",
            "result_type": "Read",
            "result_speed": 238.86160768135133,
            "color": "cadetblue"
         }
      ],
      "test_name": "CitmCatalog Test (Minified)"
   },
   {
      "results": [
         {
            "library_name": "simdjson",
            "result_type": "Read",
            "result_speed": 1016.4343973545747,
            "color": "cadetblue"
         },
         {
            "library_name": "jsonifier",
            "result_type": "Read",
            "result_speed": 307.84900284292104,
            "color": "teal"
         },
         {
            "library_name": "jsonifier",
            "result_type": "Write",
            "result_speed": 1194.6026475081828,
            "color": "steelblue"
         }
      ],
      "test_name": "Twitter Partial Test (Prettified)"
   },
   {
      "results": [
         {
            "library_name": "simdjson",
            "result_type": "Read",
            "result_speed": 891.1559483635681,
            "color": "cadetblue"
         },
         {
            "library_name": "jsonifier",
            "result_type": "Read",
            "result_speed": 312.82050552303946,
            "color": "teal"
         },
         {
            "library_name": "jsonifier",
            "result_type": "Write",
            "result_speed": 2226.511497548522,
            "color": "steelblue"
         }
      ],
      "test_name": "Twitter Partial Test (Minified)"
   },
   {
      "results": [
         {
            "library_name": "jsonifier",
            "result_type": "Read",
            "result_speed": 856.193521052669,
            "color": "teal"
         },
         {
            "library_name": "jsonifier",
            "result_type": "Write",
            "result_speed": 881.6920860941758,
            "color": "steelblue"
         },
         {
            "library_name": "glaze",
            "result_type": "Read",
            "result_speed": 645.9958703279216,
            "color": "dodgerblue"
         },
         {
            "library_name": "glaze",
            "result_type": "Write",
            "result_speed": 415.13491337994674,
            "color": "skyblue"
         },
         {
            "library_name": "simdjson",
            "result_type": "Read",
            "result_speed": 570.5336848721456,
            "color": "cadetblue"
         }
      ],
      "test_name": "Twitter Test (Prettified)"
   },
   {
      "results": [
         {
            "library_name": "jsonifier",
            "result_type": "Read",
            "result_speed": 605.4588663360885,
            "color": "teal"
         },
         {
            "library_name": "jsonifier",
            "result_type": "Write",
            "result_speed": 778.4819687832885,
            "color": "steelblue"
         },
         {
            "library_name": "glaze",
            "result_type": "Read",
            "result_speed": 469.3299891486821,
            "color": "dodgerblue"
         },
         {
            "library_name": "glaze",
            "result_type": "Write",
            "result_speed": 403.7483704542565,
            "color": "skyblue"
         },
         {
            "library_name": "simdjson",
            "result_type": "Read",
            "result_speed": 398.06275364754663,
            "color": "cadetblue"
         }
      ],
      "test_name": "Twitter Test (Minified)"
   },
   {
      "results": [
         {
            "library_name": "glaze",
            "result_type": "Write",
            "result_speed": 789.8895930086766,
            "color": "skyblue"
         },
         {
            "library_name": "simdjson",
            "result_type": "Write",
            "result_speed": 339.2014772401468,
            "color": "cornflowerblue"
         },
         {
            "library_name": "jsonifier",
            "result_type": "Write",
            "result_speed": 158.62479723606754,
            "color": "steelblue"
         }
      ],
      "test_name": "Minify Test"
   },
   {
      "results": [
         {
            "library_name": "glaze",
            "result_type": "Write",
            "result_speed": 923.50260890279,
            "color": "skyblue"
         },
         {
            "library_name": "jsonifier",
            "result_type": "Write",
            "result_speed": 877.1845984628828,
            "color": "steelblue"
         }
      ],
      "test_name": "Prettify Test"
   },
   {
      "results": [
         {
            "library_name": "glaze",
            "result_type": "Read",
            "result_speed": 2009.9394162691879,
            "color": "dodgerblue"
         },
         {
            "library_name": "jsonifier",
            "result_type": "Read",
            "result_speed": 302.8135408520472,
            "color": "teal"
         }
      ],
      "test_name": "Validate Test"
   }
]