[
   {
      "results": [
         {
            "libraryName": "jsonifier",
            "resultType": "Read",
            "resultSpeed": 1571.7640555332878,
            "color": "teal"
         },
         {
            "libraryName": "jsonifier",
            "resultType": "Write",
            "resultSpeed": 1890.29308944252,
            "color": "steelblue"
         },
         {
            "libraryName": "glaze",
            "resultType": "Read",
            "resultSpeed": 1201.6489405932546,
            "color": "dodgerblue"
         },
         {
            "libraryName": "glaze",
            "resultType": "Write",
            "resultSpeed": 1637.980467279511,
            "color": "skyblue"
         },
         {
            "libraryName": "simdjson",
            "resultType": "Read",
            "resultSpeed": 485.96345533954934,
            "color": "cadetblue"
         }
      ],
      "testName": "Json Test (Prettified)"
   },
   {
      "results": [
         {
            "libraryName": "jsonifier",
            "resultType": "Read",
            "resultSpeed": 1307.4775746598978,
            "color": "teal"
         },
         {
            "libraryName": "jsonifier",
            "resultType": "Write",
            "resultSpeed": 1620.4936268379267,
            "color": "steelblue"
         },
         {
            "libraryName": "glaze",
            "resultType": "Read",
            "resultSpeed": 1079.2013566716041,
            "color": "dodgerblue"
         },
         {
            "libraryName": "glaze",
            "resultType": "Write",
            "resultSpeed": 1484.9952037161386,
            "color": "skyblue"
         },
         {
            "libraryName": "simdjson",
            "resultType": "Read",
            "resultSpeed": 380.9132135998671,
            "color": "cadetblue"
         }
      ],
      "testName": "Json Test (Minified)"
   },
   {
      "results": [
         {
            "libraryName": "jsonifier",
            "resultType": "Read",
            "resultSpeed": 4546.863055318014,
            "color": "teal"
         },
         {
            "libraryName": "jsonifier",
            "resultType": "Write",
            "resultSpeed": 2836.7791623299504,
            "color": "steelblue"
         },
         {
            "libraryName": "glaze",
            "resultType": "Read",
            "resultSpeed": 3660.896201672769,
            "color": "dodgerblue"
         },
         {
            "libraryName": "glaze",
            "resultType": "Write",
            "resultSpeed": 2467.869010395543,
            "color": "skyblue"
         },
         {
            "libraryName": "simdjson",
            "resultType": "Read",
            "resultSpeed": 2149.7219088202796,
            "color": "cadetblue"
         }
      ],
      "testName": "Partial Test (Prettified)"
   },
   {
      "results": [
         {
            "libraryName": "jsonifier",
            "resultType": "Read",
            "resultSpeed": 5191.183507701892,
            "color": "teal"
         },
         {
            "libraryName": "jsonifier",
            "resultType": "Write",
            "resultSpeed": 2617.6244780353595,
            "color": "steelblue"
         },
         {
            "libraryName": "glaze",
            "resultType": "Read",
            "resultSpeed": 3656.39881846829,
            "color": "dodgerblue"
         },
         {
            "libraryName": "glaze",
            "resultType": "Write",
            "resultSpeed": 2269.9557415160484,
            "color": "skyblue"
         },
         {
            "libraryName": "simdjson",
            "resultType": "Read",
            "resultSpeed": 1830.546683863062,
            "color": "cadetblue"
         }
      ],
      "testName": "Partial Test (Minified)"
   },
   {
      "results": [
         {
            "libraryName": "jsonifier",
            "resultType": "Read",
            "resultSpeed": 1536.8931197510728,
            "color": "teal"
         },
         {
            "libraryName": "jsonifier",
            "resultType": "Write",
            "resultSpeed": 1855.6081615022492,
            "color": "steelblue"
         },
         {
            "libraryName": "glaze",
            "resultType": "Read",
            "resultSpeed": 1205.1391889897648,
            "color": "dodgerblue"
         },
         {
            "libraryName": "glaze",
            "resultType": "Write",
            "resultSpeed": 1658.703699206231,
            "color": "skyblue"
         },
         {
            "libraryName": "simdjson",
            "resultType": "Read",
            "resultSpeed": 102.6289933803884,
            "color": "cadetblue"
         }
      ],
      "testName": "Abc (Out of Order) Test (Prettified)"
   },
   {
      "results": [
         {
            "libraryName": "jsonifier",
            "resultType": "Read",
            "resultSpeed": 1296.3578941980777,
            "color": "teal"
         },
         {
            "libraryName": "jsonifier",
            "resultType": "Write",
            "resultSpeed": 1641.8718730050084,
            "color": "steelblue"
         },
         {
            "libraryName": "glaze",
            "resultType": "Read",
            "resultSpeed": 1066.5323471055108,
            "color": "dodgerblue"
         },
         {
            "libraryName": "glaze",
            "resultType": "Write",
            "resultSpeed": 1436.6927177239002,
            "color": "skyblue"
         },
         {
            "libraryName": "simdjson",
            "resultType": "Read",
            "resultSpeed": 80.53966193570763,
            "color": "cadetblue"
         }
      ],
      "testName": "Abc (Out of Order) Test (Minified)"
   },
   {
      "results": [
         {
            "libraryName": "jsonifier",
            "resultType": "Read",
            "resultSpeed": 1122.479550756029,
            "color": "teal"
         },
         {
            "libraryName": "jsonifier",
            "resultType": "Write",
            "resultSpeed": 2077.6326465456978,
            "color": "steelblue"
         },
         {
            "libraryName": "glaze",
            "resultType": "Read",
            "resultSpeed": 1051.5670472134868,
            "color": "dodgerblue"
         },
         {
            "libraryName": "glaze",
            "resultType": "Write",
            "resultSpeed": 1857.4764854029606,
            "color": "skyblue"
         },
         {
            "libraryName": "simdjson",
            "resultType": "Read",
            "resultSpeed": 311.0824288465633,
            "color": "cadetblue"
         }
      ],
      "testName": "Discord Test (Prettified)"
   },
   {
      "results": [
         {
            "libraryName": "glaze",
            "resultType": "Read",
            "resultSpeed": 866.6993191830222,
            "color": "dodgerblue"
         },
         {
            "libraryName": "glaze",
            "resultType": "Write",
            "resultSpeed": 1273.3548744171412,
            "color": "skyblue"
         },
         {
            "libraryName": "jsonifier",
            "resultType": "Read",
            "resultSpeed": 838.5507709576295,
            "color": "teal"
         },
         {
            "libraryName": "jsonifier",
            "resultType": "Write",
            "resultSpeed": 1725.5618865610872,
            "color": "steelblue"
         },
         {
            "libraryName": "simdjson",
            "resultType": "Read",
            "resultSpeed": 177.38899861712298,
            "color": "cadetblue"
         }
      ],
      "testName": "Discord Test (Minified)"
   },
   {
      "results": [
         {
            "libraryName": "jsonifier",
            "resultType": "Read",
            "resultSpeed": 703.3513794157949,
            "color": "teal"
         },
         {
            "libraryName": "jsonifier",
            "resultType": "Write",
            "resultSpeed": 1200.710995847656,
            "color": "steelblue"
         },
         {
            "libraryName": "glaze",
            "resultType": "Read",
            "resultSpeed": 510.29843653546567,
            "color": "dodgerblue"
         },
         {
            "libraryName": "glaze",
            "resultType": "Write",
            "resultSpeed": 1044.3667940263222,
            "color": "skyblue"
         },
         {
            "libraryName": "simdjson",
            "resultType": "Read",
            "resultSpeed": 203.1500622584652,
            "color": "cadetblue"
         }
      ],
      "testName": "Canada Test (Prettified)"
   },
   {
      "results": [
         {
            "libraryName": "jsonifier",
            "resultType": "Read",
            "resultSpeed": 569.2776320430603,
            "color": "teal"
         },
         {
            "libraryName": "jsonifier",
            "resultType": "Write",
            "resultSpeed": 450.0140487734574,
            "color": "steelblue"
         },
         {
            "libraryName": "glaze",
            "resultType": "Read",
            "resultSpeed": 367.82817258399274,
            "color": "dodgerblue"
         },
         {
            "libraryName": "glaze",
            "resultType": "Write",
            "resultSpeed": 417.3222825786067,
            "color": "skyblue"
         },
         {
            "libraryName": "simdjson",
            "resultType": "Read",
            "resultSpeed": 137.99981385064635,
            "color": "cadetblue"
         }
      ],
      "testName": "Canada Test (Minified)"
   },
   {
      "results": [
         {
            "libraryName": "jsonifier",
            "resultType": "Read",
            "resultSpeed": 1778.1807881573322,
            "color": "teal"
         },
         {
            "libraryName": "jsonifier",
            "resultType": "Write",
            "resultSpeed": 2722.1725978514346,
            "color": "steelblue"
         },
         {
            "libraryName": "glaze",
            "resultType": "Read",
            "resultSpeed": 1628.2841599407552,
            "color": "dodgerblue"
         },
         {
            "libraryName": "glaze",
            "resultType": "Write",
            "resultSpeed": 2198.0376034412025,
            "color": "skyblue"
         },
         {
            "libraryName": "simdjson",
            "resultType": "Read",
            "resultSpeed": 509.47883172387236,
            "color": "cadetblue"
         }
      ],
      "testName": "CitmCatalog Test (Prettified)"
   },
   {
      "results": [
         {
            "libraryName": "glaze",
            "resultType": "Read",
            "resultSpeed": 1308.044486302584,
            "color": "dodgerblue"
         },
         {
            "libraryName": "glaze",
            "resultType": "Write",
            "resultSpeed": 1221.9492568348371,
            "color": "skyblue"
         },
         {
            "libraryName": "jsonifier",
            "resultType": "Read",
            "resultSpeed": 1285.6107964263535,
            "color": "teal"
         },
         {
            "libraryName": "jsonifier",
            "resultType": "Write",
            "resultSpeed": 1928.9359483474043,
            "color": "steelblue"
         },
         {
            "libraryName": "simdjson",
            "resultType": "Read",
            "resultSpeed": 224.46951823111164,
            "color": "cadetblue"
         }
      ],
      "testName": "CitmCatalog Test (Minified)"
   },
   {
      "results": [
         {
            "libraryName": "jsonifier",
            "resultType": "Read",
            "resultSpeed": 1334.8531376411859,
            "color": "teal"
         },
         {
            "libraryName": "jsonifier",
            "resultType": "Write",
            "resultSpeed": 2569.256164332419,
            "color": "steelblue"
         },
         {
            "libraryName": "glaze",
            "resultType": "Read",
            "resultSpeed": 974.9747406112912,
            "color": "dodgerblue"
         },
         {
            "libraryName": "glaze",
            "resultType": "Write",
            "resultSpeed": 2259.1968713182273,
            "color": "skyblue"
         },
         {
            "libraryName": "simdjson",
            "resultType": "Read",
            "resultSpeed": 281.9888005371127,
            "color": "cadetblue"
         }
      ],
      "testName": "Twitter Test (Prettified)"
   },
   {
      "results": [
         {
            "libraryName": "jsonifier",
            "resultType": "Read",
            "resultSpeed": 1241.1535856170603,
            "color": "teal"
         },
         {
            "libraryName": "jsonifier",
            "resultType": "Write",
            "resultSpeed": 2581.020582364535,
            "color": "steelblue"
         },
         {
            "libraryName": "glaze",
            "resultType": "Read",
            "resultSpeed": 900.8036664764552,
            "color": "dodgerblue"
         },
         {
            "libraryName": "glaze",
            "resultType": "Write",
            "resultSpeed": 2108.5133778870436,
            "color": "skyblue"
         },
         {
            "libraryName": "simdjson",
            "resultType": "Read",
            "resultSpeed": 211.27471940480106,
            "color": "cadetblue"
         }
      ],
      "testName": "Twitter Test (Minified)"
   },
   {
      "results": [
         {
            "libraryName": "glaze",
            "resultType": "Write",
            "resultSpeed": 994.2642217195158,
            "color": "skyblue"
         },
         {
            "libraryName": "jsonifier",
            "resultType": "Write",
            "resultSpeed": 890.8732351165951,
            "color": "steelblue"
         },
         {
            "libraryName": "simdjson",
            "resultType": "Write",
            "resultSpeed": 570.3138130541286,
            "color": "cornflowerblue"
         }
      ],
      "testName": "Minify Test"
   },
   {
      "results": [
         {
            "libraryName": "glaze",
            "resultType": "Write",
            "resultSpeed": 1213.6734481483206,
            "color": "skyblue"
         },
         {
            "libraryName": "jsonifier",
            "resultType": "Write",
            "resultSpeed": 1113.0099206816735,
            "color": "steelblue"
         }
      ],
      "testName": "Prettify Test"
   },
   {
      "results": [
         {
            "libraryName": "jsonifier",
            "resultType": "Read",
            "resultSpeed": 2591.1162572681383,
            "color": "teal"
         },
         {
            "libraryName": "glaze",
            "resultType": "Read",
            "resultSpeed": 1157.8145206471172,
            "color": "skyblue"
         }
      ],
      "testName": "Validate Test"
   }
]