[
   {
      "results": [
         {
            "libraryName": "jsonifier",
            "resultType": "Read",
            "resultSpeed": 1298.0355911741347,
            "iterationCount": 300,
            "color": "teal"
         },
         {
            "libraryName": "jsonifier",
            "resultType": "Write",
            "resultSpeed": 1285.4596725364033,
            "iterationCount": 300,
            "color": "steelblue"
         },
         {
            "libraryName": "glaze",
            "resultType": "Read",
            "resultSpeed": 767.3578730881034,
            "iterationCount": 300,
            "color": "dodgerblue"
         },
         {
            "libraryName": "glaze",
            "resultType": "Write",
            "resultSpeed": 1295.6181499676254,
            "iterationCount": 300,
            "color": "skyblue"
         },
         {
            "libraryName": "simdjson",
            "resultType": "Read",
            "resultSpeed": 300.124020564296,
            "iterationCount": 300,
            "color": "cadetblue"
         }
      ],
      "testName": "Json Test (Prettified)"
   },
   {
      "results": [
         {
            "libraryName": "jsonifier",
            "resultType": "Read",
            "resultSpeed": 954.5191542388551,
            "iterationCount": 300,
            "color": "teal"
         },
         {
            "libraryName": "jsonifier",
            "resultType": "Write",
            "resultSpeed": 1015.7361982850107,
            "iterationCount": 300,
            "color": "steelblue"
         },
         {
            "libraryName": "glaze",
            "resultType": "Read",
            "resultSpeed": 614.6436892685906,
            "iterationCount": 300,
            "color": "dodgerblue"
         },
         {
            "libraryName": "glaze",
            "resultType": "Write",
            "resultSpeed": 1063.6634603324408,
            "iterationCount": 298,
            "color": "skyblue"
         },
         {
            "libraryName": "simdjson",
            "resultType": "Read",
            "resultSpeed": 195.80958454813688,
            "iterationCount": 300,
            "color": "cadetblue"
         }
      ],
      "testName": "Json Test (Minified)"
   },
   {
      "results": [
         {
            "libraryName": "jsonifier",
            "resultType": "Read",
            "resultSpeed": 1382.0359757582974,
            "iterationCount": 194,
            "color": "teal"
         },
         {
            "libraryName": "jsonifier",
            "resultType": "Write",
            "resultSpeed": 1328.3629158004278,
            "iterationCount": 97,
            "color": "steelblue"
         },
         {
            "libraryName": "glaze",
            "resultType": "Read",
            "resultSpeed": 833.6227956689045,
            "iterationCount": 289,
            "color": "dodgerblue"
         },
         {
            "libraryName": "glaze",
            "resultType": "Write",
            "resultSpeed": 1426.749176835222,
            "iterationCount": 174,
            "color": "skyblue"
         },
         {
            "libraryName": "simdjson",
            "resultType": "Read",
            "resultSpeed": 84.47094419657265,
            "iterationCount": 234,
            "color": "cadetblue"
         }
      ],
      "testName": "Abc Test (Prettified)"
   },
   {
      "results": [
         {
            "libraryName": "jsonifier",
            "resultType": "Read",
            "resultSpeed": 1033.74917820161,
            "iterationCount": 96,
            "color": "teal"
         },
         {
            "libraryName": "jsonifier",
            "resultType": "Write",
            "resultSpeed": 1124.6511095389321,
            "iterationCount": 98,
            "color": "steelblue"
         },
         {
            "libraryName": "glaze",
            "resultType": "Read",
            "resultSpeed": 638.6375156342965,
            "iterationCount": 178,
            "color": "dodgerblue"
         },
         {
            "libraryName": "glaze",
            "resultType": "Write",
            "resultSpeed": 1079.1073002281682,
            "iterationCount": 290,
            "color": "skyblue"
         },
         {
            "libraryName": "simdjson",
            "resultType": "Read",
            "resultSpeed": 57.593295261982504,
            "iterationCount": 97,
            "color": "cadetblue"
         }
      ],
      "testName": "Abc Test (Minified)"
   },
   {
      "results": [
         {
            "libraryName": "jsonifier",
            "resultType": "Read",
            "resultSpeed": 1432.7811138743696,
            "iterationCount": 96,
            "color": "teal"
         },
         {
            "libraryName": "jsonifier",
            "resultType": "Write",
            "resultSpeed": 1967.1157909919598,
            "iterationCount": 98,
            "color": "steelblue"
         },
         {
            "libraryName": "glaze",
            "resultType": "Read",
            "resultSpeed": 1109.2245611494668,
            "iterationCount": 298,
            "color": "dodgerblue"
         },
         {
            "libraryName": "glaze",
            "resultType": "Write",
            "resultSpeed": 1922.6165299236977,
            "iterationCount": 200,
            "color": "skyblue"
         },
         {
            "libraryName": "simdjson",
            "resultType": "Read",
            "resultSpeed": 90.91605002495646,
            "iterationCount": 97,
            "color": "cadetblue"
         }
      ],
      "testName": "Discord Test (Prettified)"
   },
   {
      "results": [
         {
            "libraryName": "jsonifier",
            "resultType": "Read",
            "resultSpeed": 892.9351680663469,
            "iterationCount": 99,
            "color": "teal"
         },
         {
            "libraryName": "jsonifier",
            "resultType": "Write",
            "resultSpeed": 1391.1001947328823,
            "iterationCount": 97,
            "color": "steelblue"
         },
         {
            "libraryName": "glaze",
            "resultType": "Read",
            "resultSpeed": 747.9824504143265,
            "iterationCount": 299,
            "color": "dodgerblue"
         },
         {
            "libraryName": "glaze",
            "resultType": "Write",
            "resultSpeed": 1283.7997884618562,
            "iterationCount": 99,
            "color": "skyblue"
         },
         {
            "libraryName": "simdjson",
            "resultType": "Read",
            "resultSpeed": 44.81436343946003,
            "iterationCount": 161,
            "color": "cadetblue"
         }
      ],
      "testName": "Discord Test (Minified)"
   },
   {
      "results": [
         {
            "libraryName": "jsonifier",
            "resultType": "Read",
            "resultSpeed": 1520.9363040684957,
            "iterationCount": 97,
            "color": "teal"
         },
         {
            "libraryName": "jsonifier",
            "resultType": "Write",
            "resultSpeed": 1089.6874165117217,
            "iterationCount": 97,
            "color": "steelblue"
         },
         {
            "libraryName": "glaze",
            "resultType": "Read",
            "resultSpeed": 1113.6441598560136,
            "iterationCount": 178,
            "color": "dodgerblue"
         },
         {
            "libraryName": "glaze",
            "resultType": "Write",
            "resultSpeed": 1118.6655469129166,
            "iterationCount": 97,
            "color": "skyblue"
         },
         {
            "libraryName": "simdjson",
            "resultType": "Read",
            "resultSpeed": 448.2108134811345,
            "iterationCount": 242,
            "color": "cadetblue"
         }
      ],
      "testName": "Canada Test (Prettified)"
   },
   {
      "results": [
         {
            "libraryName": "jsonifier",
            "resultType": "Read",
            "resultSpeed": 490.2365091089797,
            "iterationCount": 97,
            "color": "teal"
         },
         {
            "libraryName": "jsonifier",
            "resultType": "Write",
            "resultSpeed": 450.38594178312337,
            "iterationCount": 97,
            "color": "steelblue"
         },
         {
            "libraryName": "glaze",
            "resultType": "Read",
            "resultSpeed": 362.8267115449677,
            "iterationCount": 96,
            "color": "dodgerblue"
         },
         {
            "libraryName": "glaze",
            "resultType": "Write",
            "resultSpeed": 432.12257517058543,
            "iterationCount": 98,
            "color": "skyblue"
         },
         {
            "libraryName": "simdjson",
            "resultType": "Read",
            "resultSpeed": 143.21035976006348,
            "iterationCount": 165,
            "color": "cadetblue"
         }
      ],
      "testName": "Canada Test (Minified)"
   },
   {
      "results": [
         {
            "libraryName": "jsonifier",
            "resultType": "Read",
            "resultSpeed": 2792.7488863809826,
            "iterationCount": 97,
            "color": "teal"
         },
         {
            "libraryName": "jsonifier",
            "resultType": "Write",
            "resultSpeed": 2246.1771619908436,
            "iterationCount": 159,
            "color": "steelblue"
         },
         {
            "libraryName": "glaze",
            "resultType": "Read",
            "resultSpeed": 1991.0823546866943,
            "iterationCount": 98,
            "color": "dodgerblue"
         },
         {
            "libraryName": "glaze",
            "resultType": "Write",
            "resultSpeed": 2432.096704886422,
            "iterationCount": 98,
            "color": "skyblue"
         },
         {
            "libraryName": "simdjson",
            "resultType": "Read",
            "resultSpeed": 629.7735197113158,
            "iterationCount": 99,
            "color": "cadetblue"
         }
      ],
      "testName": "CitmCatalog Test (Prettified)"
   },
   {
      "results": [
         {
            "libraryName": "jsonifier",
            "resultType": "Read",
            "resultSpeed": 1684.3980027582636,
            "iterationCount": 97,
            "color": "teal"
         },
         {
            "libraryName": "jsonifier",
            "resultType": "Write",
            "resultSpeed": 1599.1242497058965,
            "iterationCount": 98,
            "color": "steelblue"
         },
         {
            "libraryName": "glaze",
            "resultType": "Read",
            "resultSpeed": 1084.2847290288219,
            "iterationCount": 97,
            "color": "dodgerblue"
         },
         {
            "libraryName": "glaze",
            "resultType": "Write",
            "resultSpeed": 1383.2812320861458,
            "iterationCount": 180,
            "color": "skyblue"
         },
         {
            "libraryName": "simdjson",
            "resultType": "Read",
            "resultSpeed": 226.500785568098,
            "iterationCount": 228,
            "color": "cadetblue"
         }
      ],
      "testName": "CitmCatalog Test (Minified)"
   },
   {
      "results": [
         {
            "libraryName": "jsonifier",
            "resultType": "Read",
            "resultSpeed": 1568.9743478387181,
            "iterationCount": 98,
            "color": "teal"
         },
         {
            "libraryName": "jsonifier",
            "resultType": "Write",
            "resultSpeed": 2238.4945675652866,
            "iterationCount": 97,
            "color": "steelblue"
         },
         {
            "libraryName": "glaze",
            "resultType": "Read",
            "resultSpeed": 1068.5230631520585,
            "iterationCount": 96,
            "color": "dodgerblue"
         },
         {
            "libraryName": "glaze",
            "resultType": "Write",
            "resultSpeed": 2404.7458338144716,
            "iterationCount": 99,
            "color": "skyblue"
         },
         {
            "libraryName": "simdjson",
            "resultType": "Read",
            "resultSpeed": 321.1836110242462,
            "iterationCount": 97,
            "color": "cadetblue"
         }
      ],
      "testName": "Twitter Test (Prettified)"
   },
   {
      "results": [
         {
            "libraryName": "jsonifier",
            "resultType": "Read",
            "resultSpeed": 1297.5445015922073,
            "iterationCount": 99,
            "color": "teal"
         },
         {
            "libraryName": "jsonifier",
            "resultType": "Write",
            "resultSpeed": 2286.7091222153745,
            "iterationCount": 97,
            "color": "steelblue"
         },
         {
            "libraryName": "glaze",
            "resultType": "Read",
            "resultSpeed": 856.8384048276366,
            "iterationCount": 161,
            "color": "dodgerblue"
         },
         {
            "libraryName": "glaze",
            "resultType": "Write",
            "resultSpeed": 2028.854881306845,
            "iterationCount": 97,
            "color": "skyblue"
         },
         {
            "libraryName": "simdjson",
            "resultType": "Read",
            "resultSpeed": 207.42427528032377,
            "iterationCount": 96,
            "color": "cadetblue"
         }
      ],
      "testName": "Twitter Test (Minified)"
   },
   {
      "results": [
         {
            "libraryName": "glaze",
            "resultType": "Write",
            "resultSpeed": 517.4000459805235,
            "iterationCount": 298,
            "color": "skyblue"
         },
         {
            "libraryName": "jsonifier",
            "resultType": "Write",
            "resultSpeed": 474.89904275230856,
            "iterationCount": 98,
            "color": "steelblue"
         },
         {
            "libraryName": "simdjson",
            "resultType": "Write",
            "resultSpeed": 285.9415265921854,
            "iterationCount": 98,
            "color": "cornflowerblue"
         }
      ],
      "testName": "Minify Test"
   },
   {
      "results": [
         {
            "libraryName": "glaze",
            "resultType": "Write",
            "resultSpeed": 1282.2178799593808,
            "iterationCount": 173,
            "color": "skyblue"
         },
         {
            "libraryName": "jsonifier",
            "resultType": "Write",
            "resultSpeed": 1243.3741082967474,
            "iterationCount": 167,
            "color": "steelblue"
         }
      ],
      "testName": "Prettify Test"
   },
   {
      "results": [
         {
            "libraryName": "jsonifier",
            "resultType": "Read",
            "resultSpeed": 2241.843349267452,
            "iterationCount": 99,
            "color": "teal"
         },
         {
            "libraryName": "glaze",
            "resultType": "Read",
            "resultSpeed": 1343.4650147451318,
            "iterationCount": 99,
            "color": "skyblue"
         }
      ],
      "testName": "Validate Test"
   }
]